datamanager_hjy/__init__.py
datamanager_hjy/cli.py
datamanager_hjy/adapters/__init__.py
datamanager_hjy/adapters/base.py
datamanager_hjy/adapters/factory.py
datamanager_hjy/adapters/mysql.py
datamanager_hjy/adapters/postgresql.py
datamanager_hjy/adapters/sqlite.py
datamanager_hjy/core/__init__.py
datamanager_hjy/core/config.py
datamanager_hjy/core/connection.py
datamanager_hjy/core/manager.py
datamanager_hjy/models/__init__.py
datamanager_hjy/models/base.py
datamanager_hjy/models/manager.py
datamanager_hjy/models/registry.py
datamanager_hjy/operations/__init__.py
datamanager_hjy/operations/batch_operator.py
datamanager_hjy/operations/query_builder.py
datamanager_hjy/operations/transaction_manager.py
datamanager_hjy/utils/__init__.py
datamanager_hjy/utils/cache.py
datamanager_hjy/utils/exceptions.py
datamanager_hjy/utils/monitoring.py
datamanager_hjy-0.3.0.dist-info/licenses/LICENSE
datamanager_hjy-0.3.0.dist-info/METADATA
datamanager_hjy-0.3.0.dist-info/WHEEL
datamanager_hjy-0.3.0.dist-info/entry_points.txt
datamanager_hjy-0.3.0.dist-info/top_level.txt
datamanager_hjy-0.3.0.dist-info/RECORD
