Metadata-Version: 2.4
Name: datamanager-hjy
Version: 0.3.0
Summary: 通用的数据管理脚手架，支持多数据库、配置驱动、高性能
Author-email: hjy <hjy@example.com>
Maintainer-email: hjy <hjy@example.com>
License: MIT
Project-URL: Homepage, https://github.com/hjy/datamanager-hjy
Project-URL: Documentation, https://datamanager-hjy.readthedocs.io/
Project-URL: Repository, https://github.com/hjy/datamanager-hjy.git
Project-URL: Bug Tracker, https://github.com/hjy/datamanager_hjy/issues
Project-URL: Source Code, https://github.com/hjy/datamanager_hjy
Project-URL: Download, https://pypi.org/project/datamanager-hjy/#files
Keywords: database,orm,sqlalchemy,mysql,postgresql,sqlite,data-management
Classifier: Development Status :: 3 - Alpha
Classifier: Intended Audience :: Developers
Classifier: License :: OSI Approved :: MIT License
Classifier: Programming Language :: Python :: 3
Classifier: Programming Language :: Python :: 3.8
Classifier: Programming Language :: Python :: 3.9
Classifier: Programming Language :: Python :: 3.10
Classifier: Programming Language :: Python :: 3.11
Classifier: Programming Language :: Python :: 3.12
Classifier: Programming Language :: Python :: 3.13
Classifier: Topic :: Database
Classifier: Topic :: Software Development :: Libraries :: Python Modules
Classifier: Topic :: Software Development :: Libraries :: Application Frameworks
Classifier: Operating System :: OS Independent
Requires-Python: >=3.8
License-File: LICENSE
Requires-Dist: sqlalchemy<3.0.0,>=2.0.0
Requires-Dist: pymysql<2.0.0,>=1.0.0
Requires-Dist: psycopg2-binary<3.0.0,>=2.9.0
Requires-Dist: redis<5.0.0,>=4.5.0
Requires-Dist: pydantic<3.0.0,>=2.0.0
Requires-Dist: loguru<1.0.0,>=0.7.0
Requires-Dist: pyyaml<7.0.0,>=6.0.0
Requires-Dist: typing-extensions<5.0.0,>=4.0.0
Provides-Extra: dev
Requires-Dist: pytest<8.0.0,>=7.0.0; extra == "dev"
Requires-Dist: pytest-cov<5.0.0,>=4.0.0; extra == "dev"
Requires-Dist: pytest-asyncio<1.0.0,>=0.21.0; extra == "dev"
Requires-Dist: black<24.0.0,>=23.0.0; extra == "dev"
Requires-Dist: isort<6.0.0,>=5.12.0; extra == "dev"
Requires-Dist: mypy<2.0.0,>=1.0.0; extra == "dev"
Requires-Dist: flake8<7.0.0,>=6.0.0; extra == "dev"
Requires-Dist: pre-commit<4.0.0,>=3.0.0; extra == "dev"
Provides-Extra: mysql
Requires-Dist: pymysql<2.0.0,>=1.0.0; extra == "mysql"
Requires-Dist: cryptography<4.0.0,>=3.4.0; extra == "mysql"
Provides-Extra: postgresql
Requires-Dist: psycopg2-binary<3.0.0,>=2.9.0; extra == "postgresql"
Provides-Extra: sqlite
Provides-Extra: redis
Requires-Dist: redis<5.0.0,>=4.5.0; extra == "redis"
Requires-Dist: hiredis<3.0.0,>=2.0.0; extra == "redis"
Dynamic: license-file
